PythonYGraph-1.1.data/scripts/pygraph
pygraph/__init__.py
pygraph/common.py
pygraph/dataeditor.py
pygraph/datasets.py
pygraph/hardcopy.py
pygraph/helpbrowser.py
pygraph/mainwindow.py
pygraph/plotsettings.py
pygraph/plotwidget.py
pygraph/resources.py
pygraph/data/dialog-error.svg
pygraph/data/document-open.svg
pygraph/data/document-save-as.svg
pygraph/data/file-view-refresh.svg
pygraph/data/help-browser.svg
pygraph/data/help.html
pygraph/data/media-playback-pause.svg
pygraph/data/media-playback-start.svg
pygraph/data/media-playback-stop.svg
pygraph/data/media-skip-backward.svg
pygraph/data/media-skip-forward.svg
pygraph/data/media-step-backward.svg
pygraph/data/media-step-forward.svg
pygraph/data/system-log-out.svg
scidata/monodataset.py
scidata/plain.py
scidata/pygraph.py
scidata/utils.py
scidata/xgraph.py
scidata/carpet/ascii.py
scidata/carpet/grid.py
scidata/carpet/hdf5.py
PythonYGraph-1.1.dist-info/AUTHORS
PythonYGraph-1.1.dist-info/LICENSE
PythonYGraph-1.1.dist-info/METADATA
PythonYGraph-1.1.dist-info/WHEEL
PythonYGraph-1.1.dist-info/top_level.txt
PythonYGraph-1.1.dist-info/RECORD
